pytest_tmux/__init__.py
pytest_tmux/client.py
pytest_tmux/config.py
pytest_tmux/fixtures.py
pytest_tmux/output.py
pytest_tmux/plugin.py
pytest_tmux/rewrite.py
pytest_tmux-0.0.5.dist-info/entry_points.txt
pytest_tmux-0.0.5.dist-info/WHEEL
pytest_tmux-0.0.5.dist-info/METADATA
pytest_tmux-0.0.5.dist-info/LICENSE
pytest_tmux-0.0.5.dist-info/RECORD
