Metadata-Version: 2.1
Name: pytest-tmux
Version: 0.0.5
Summary: A pytest plugin that enables tmux driven tests
Home-page: https://github.com/rockandska/pytest-tmux
License: MIT
Author: rockandska
Author-email: yoann_mac_donald@hotmail.com
Requires-Python: >=3.7,<=3.11.9999
Classifier: Development Status :: 4 - Beta
Classifier: Framework :: Pytest
Classifier: Intended Audience :: Developers
Classifier: License :: OSI Approved :: MIT License
Classifier: Operating System :: OS Independent
Classifier: Programming Language :: Python
Classifier: Programming Language :: Python :: 3
Classifier: Programming Language :: Python :: 3.7
Classifier: Programming Language :: Python :: 3.8
Classifier: Programming Language :: Python :: 3.9
Classifier: Programming Language :: Python :: 3.10
Classifier: Programming Language :: Python :: 3.11
Classifier: Programming Language :: Python :: 3.10
Classifier: Programming Language :: Python :: 3.11
Classifier: Programming Language :: Python :: 3.7
Classifier: Programming Language :: Python :: 3.8
Classifier: Programming Language :: Python :: 3.9
Classifier: Topic :: Software Development :: Testing
Classifier: Typing :: Typed
Requires-Dist: libtmux (==0.20)
Project-URL: Changes, https://github.com/rockandska/pytest-tmux/blob/master/CHANGELOG.md
Project-URL: Documentation, https://pytest-tmux.readthedocs.io
Project-URL: Issues, https://github.com/rockandska/pytest-tmux/issues
Project-URL: Repository, https://github.com/rockandska/pytest-tmux.git
